integerSequence/__init__.py
integerSequence/factorial.py
integerSequence/hofstadter.py
integerSequence/horadam.py
integerSequence/integerSequence.py
integerSequence/padovan.py
integerSequence/pellLucas.py
integerSequence/polygonal.py
integerSequence/polyhedral.py
integerSequence/prime.py
integerSequence-0.1.1.data/data/LICENSE.md
integerSequence-0.1.1.data/data/README.md
integerSequence-0.1.1.dist-info/METADATA
integerSequence-0.1.1.dist-info/RECORD
integerSequence-0.1.1.dist-info/WHEEL
integerSequence-0.1.1.dist-info/top_level.txt
