Metadata-Version: 2.1
Name: integerSequence
Version: 0.1.1
Summary: A Package for natively representing and calculating common integer sequences
Home-page: https://github.com/vigilance91/integerSequences-py
Author: Tyler R. Drury
Author-email: that_canadianguy@hotmail.com
Maintainer: Tyler R. Drury
Maintainer-email: that_canadianguy@hotmail.com
License: UNKNOWN
Platform: UNKNOWN
Classifier: Development Status :: 3 - Alpha
Classifier: License :: OSI Approved :: Apache Software License
Classifier: Environment :: Win32 (MS Windows)
Classifier: Environment :: Console
Classifier: Natural Language :: English
Classifier: Operating System :: Microsoft
Classifier: Operating System :: Microsoft :: Windows :: Windows 8
Classifier: Programming Language :: Python
Classifier: Programming Language :: Python :: 3
Classifier: Programming Language :: Python :: 3.4
Classifier: Programming Language :: Python :: 3 :: Only
Classifier: Intended Audience :: Developers
Classifier: Intended Audience :: Education
Classifier: Intended Audience :: End Users/Desktop
Classifier: Intended Audience :: Other Audience
Classifier: Intended Audience :: Science/Research
Classifier: Topic :: Education
Classifier: Topic :: Games/Entertainment
Classifier: Topic :: Scientific/Engineering :: Mathematics
Classifier: Topic :: Software Development :: Libraries
Classifier: Topic :: Software Development :: Libraries :: Python Modules
Classifier: Topic :: Utilities
